biosmoother/VERSION
biosmoother/__init__.py
biosmoother/app_hooks.py
biosmoother/cli.py
biosmoother/main.py
biosmoother/bin/__init__.py
biosmoother/bin/extra_ticks_ticker.py
biosmoother/bin/figure_maker.py
biosmoother/bin/global_variables.py
biosmoother/bin/main_layout.py
biosmoother/static/__init__.py
biosmoother/static/error.png
biosmoother/static/favicon.ico
biosmoother/static/favicon.png
biosmoother/static/favicon.svg
biosmoother/static/stirring.gif
biosmoother/static/conf/1.json
biosmoother/static/conf/2.json
biosmoother/static/conf/3.json
biosmoother/static/conf/4.json
biosmoother/static/conf/5.json
biosmoother/static/conf/6.json
biosmoother/static/conf/__init__.py
biosmoother/static/conf/descriptions.json
biosmoother/static/css/__init__.py
biosmoother/static/css/floppy-disk-hover.svg
biosmoother/static/css/floppy-disk-solid.svg
biosmoother/static/css/page-next-hover.svg
biosmoother/static/css/page-next-solid.svg
biosmoother/static/css/page-next.svg
biosmoother/static/css/page-previous-hover.svg
biosmoother/static/css/page-previous-solid.svg
biosmoother/static/css/page-previous.svg
biosmoother/static/css/play-button-disabled.svg
biosmoother/static/css/play-button-hover.svg
biosmoother/static/css/play-button.svg
biosmoother/static/css/repeat-solid-disabled.svg
biosmoother/static/css/repeat-solid-hover.svg
biosmoother/static/css/repeat-solid.svg
biosmoother/static/css/sort-down-solid.svg
biosmoother/static/css/sort-up-solid.svg
biosmoother/static/css/styles.css
biosmoother/static/css/tooltips.css
biosmoother/static/css/tooltips_generated.css
biosmoother/templates/__init__.py
biosmoother/templates/index.html
biosmoother-1.6.1.data/data/biosmoother/VERSION
biosmoother-1.6.1.dist-info/LICENSE
biosmoother-1.6.1.dist-info/METADATA
biosmoother-1.6.1.dist-info/WHEEL
biosmoother-1.6.1.dist-info/entry_points.txt
biosmoother-1.6.1.dist-info/top_level.txt
biosmoother-1.6.1.dist-info/RECORD
